{"type":"FeatureCollection","features":[{"type":"Feature","geometry":{"type":"Point","coordinates":[44.361572,33.958]},"properties":{"Installation Name":"Ballad Air Base/Camp Anaconda"}},{"type":"Feature","geometry":{"type":"Point","coordinates":[26.352219,42.454]},"properties":{"Installation Name":"Bezmer Air Base"}},{"type":"Feature","geometry":{"type":"Point","coordinates":[74.466,43.049]},"properties":{"Installation Name":"Manas Air Force Base"}}]}