{"type":"FeatureCollection","features":[{"type":"Feature","geometry":{"type":"Point","coordinates":[44.361572,33.958]},"properties":{"Installation Name":"Ballad Air Base/Camp Anaconda"}},{"type":"Feature","geometry":{"type":"Point","coordinates":[72.407,-7.305]},"properties":{"Installation Name":"Diego Garcia"}},{"type":"Feature","geometry":{"type":"Point","coordinates":[74.466,43.049]},"properties":{"Installation Name":"Manas Air Force Base"}},{"type":"Feature","properties":{},"geometry":{"type":"Point","coordinates":[77.080078125,28.748396571187406]}}]}